kwiki/__init__.py
kwiki/kwiki.py
kwiki/wikiferheng.json
kwiki/data/__init__.py
kwiki/data/wikiferheng.json
kwiki-0.0.8.dist-info/METADATA
kwiki-0.0.8.dist-info/WHEEL
kwiki-0.0.8.dist-info/top_level.txt
kwiki-0.0.8.dist-info/RECORD
