Metadata-Version: 2.1
Name: kwiki
Version: 0.0.8
Summary: A parser of the Kurdish wiktionary (Wikiferheng)
Home-page: https://github.com/kurd-cc/kwiki
Author: Jagar Yousef
Author-email: <jagar.yousef@gmail.com>
License: UNKNOWN
Keywords: kurdish,language,language-processing,kurmanji,wiktionary,parser
Platform: UNKNOWN
Classifier: Development Status :: 1 - Planning
Classifier: Intended Audience :: Developers
Classifier: Programming Language :: Python :: 3
Classifier: Operating System :: Unix
Classifier: Operating System :: MacOS :: MacOS X
Classifier: Operating System :: Microsoft :: Windows
